MANIFEST.in
README.rst
setup.cfg
setup.py
pytypewriter/__init__.py
pytypewriter/errors.py
pytypewriter/exchange.py
pytypewriter/types.py
pytypewriter/version.py
pytypewriter.egg-info/PKG-INFO
pytypewriter.egg-info/SOURCES.txt
pytypewriter.egg-info/dependency_links.txt
pytypewriter.egg-info/entry_points.txt
pytypewriter.egg-info/top_level.txt