Metadata-Version: 1.2
Name: pytypewriter
Version: 0.0.7
Summary: This is a simple library to help you serialize Python type names and call them up again when you need them.
Home-page: https://github.com/patdaburu/pytypewriter
Author: Pat Daburu
Author-email: pat@daburu.net
License: MIT
Download-URL: https://github.com/patdaburu/pytypewriter/archive/0.0.7.tar.gz
Platform: UNKNOWN
Classifier: Development Status :: 3 - Alpha
Classifier: Intended Audience :: Developers
Classifier: Topic :: Software Development :: Libraries
Classifier: License :: OSI Approved :: MIT License
Classifier: Programming Language :: Python :: 3.6
Requires-Python: >=0.0.1
